{"Q7645320": {"IMDb ID": ["tt0952685"], "instance of": ["film"], "director": ["T L V Prasad"], "cast member": ["Mithun Chakraborty", "Ayesha Jhulka", "Puneet Issar", "Mohan Joshi"], "publication date": [{"time": "+1997-01-01T00:00:00Z", "timezone": 0, "before": 0, "after": 0, "precision": 9, "calendarmodel": "http://www.wikidata.org/entity/Q1985727"}], "filming location": ["Ooty"], "original language of film or TV show": ["Hindi"], "country of origin": ["India"], "Kinopoisk film ID": ["278356"], "color": ["color"], "\u010cSFD film ID": ["289758"], "Rotten Tomatoes ID": ["m/suraj"], "composer": ["Anand-Milind"], "Indiancine.ma film ID": ["APRJ"]}, "Q7645326": {"IMDb ID": ["tt0108256"], "instance of": ["film"], "director": ["Shyam Benegal"], "cast member": ["Rajit Kapur", "Amrish Puri", "Neena Gupta", "Rajeshwari Sachdev", "Pallavi Joshi", "K. K. Raina", "Ravi Jhankal", "Raghubir Yadav", "Ila Arun", "Himani Shivpuri", "Virendra Saxena", "Lalit Mohan Tiwari", "Anang Desai", "Rupal Patel"], "original language of film or TV show": ["Hindi"], "publication date": [{"time": "+1992-01-01T00:00:00Z", "timezone": 0, "before": 0, "after": 0, "precision": 9, "calendarmodel": "http://www.wikidata.org/entity/Q1985727"}], "country of origin": ["India"], "composer": ["Vanraj Bhatia"], "color": ["color"], "Kinopoisk film ID": ["86783"], "FilmAffinity ID": ["560840"], "Rotten Tomatoes ID": ["m/suraj-ka-satvan-ghoda-seventh-horse-of-the-sun"], "AllMovie movie ID": ["v224680"], "elFilm film ID": ["107816"], "\u010cSFD film ID": ["195768"], "PORT film ID": ["118817"], "based on": ["The Sun's Seventh Horse"], "duration": [{"amount": "+130", "unit": "http://www.wikidata.org/entity/Q7727"}], "screenwriter": ["Shama Zaidi"], "genre": ["art film", "metafiction", "film based on literature"], "award received": ["National Film Award for Best Feature Film in Hindi"], "production company": ["National Film Development Corporation of India"]}, "Q7645359": {"IMDb ID": ["tt0343048"], "instance of": ["film"], "cast member": ["Saif Ali Khan", "Aditya Pancholi", "Sunil Shetty", "Divya Dutta", "Monica Bedi"], "publication date": [{"time": "+1995-01-01T00:00:00Z", "timezone": 0, "before": 0, "after": 0, "precision": 9, "calendarmodel": "http://www.wikidata.org/entity/Q1985727"}], "original language of film or TV show": ["Hindi"], "country of origin": ["India"], "Kinopoisk film ID": ["96966"], "composer": ["Anu Malik"], "color": ["color"], "elFilm film ID": ["338254"], "\u010cSFD film ID": ["174157"], "director": ["Raju Mavani"]}, "Q7490659": {"IMDb ID": ["tt0108109"], "instance of": ["film"], "director": ["Aziz Sejawal"], "cast member": ["Mithun Chakraborty", "Jackie Shroff", "Juhi Chawla", "Divya Bharti"], "publication date": [{"time": "+1993-01-01T00:00:00Z", "timezone": 0, "before": 0, "after": 0, "precision": 9, "calendarmodel": "http://www.wikidata.org/entity/Q1985727"}], "original language of film or TV show": ["Hindi"], "country of origin": ["India"], "Kinopoisk film ID": ["36612"], "OFDb ID": ["225762"], "color": ["color"], "elFilm film ID": ["107670"], "\u010cSFD film ID": ["266281"], "composer": ["Anand-Milind"]}}