{"Q12416751": {"instance of": ["film"], "publication date": [{"time": "+1968-00-00T00:00:00Z", "timezone": 0, "before": 0, "after": 0, "precision": 9, "calendarmodel": "http://www.wikidata.org/entity/Q1985727"}], "country of origin": ["India"], "original language of film or TV show": ["Hindi"], "IMDb ID": ["tt0230176"], "director": ["Vasant Joglekar"], "composer": ["Madan Mohan"]}, "Q12417531": {"instance of": ["film"], "publication date": [{"time": "+1959-00-00T00:00:00Z", "timezone": 0, "before": 0, "after": 0, "precision": 9, "calendarmodel": "http://www.wikidata.org/entity/Q1985727"}], "country of origin": ["India"], "original language of film or TV show": ["Hindi"], "cast member": ["Nirupa Roy"]}, "Q12417852": {"instance of": ["film"], "publication date": [{"time": "+1963-00-00T00:00:00Z", "timezone": 0, "before": 0, "after": 0, "precision": 9, "calendarmodel": "http://www.wikidata.org/entity/Q1985727"}], "country of origin": ["India"], "original language of film or TV show": ["Hindi"], "IMDb ID": ["tt0242570"]}, "Q12418180": {"instance of": ["film", "television series"], "publication date": [{"time": "+1997-00-00T00:00:00Z", "timezone": 0, "before": 0, "after": 0, "precision": 9, "calendarmodel": "http://www.wikidata.org/entity/Q1985727"}], "country of origin": ["India"], "original language of film or TV show": ["Hindi"], "director": ["Mahesh Bhatt"], "IMDb ID": ["tt0307763"]}}