{"Q4875399": {"IMDb ID": ["tt1869296"], "instance of": ["film"], "director": ["Puri Jagannadh"], "cast member": ["Amitabh Bachchan", "Hema Malini", "Sonu Sood", "Prakash Raj", "Sonal Chauhan", "Raveena Tandon", "Charmy Kaur"], "original language of film or TV show": ["Hindi"], "producer": ["Abhishek Bachchan", "Viacom 18 Motion Pictures"], "official website": ["http://www.bigbisback.com"], "publication date": [{"time": "+2011-01-01T00:00:00Z", "timezone": 0, "before": 0, "after": 0, "precision": 9, "calendarmodel": "http://www.wikidata.org/entity/Q1985727"}], "country of origin": ["India"], "distributed by": ["Amitabh Bachchan Corporation"], "director of photography": ["Amol Rathod"], "Freebase ID": ["/m/0gmcprl"], "OFDb ID": ["225546"], "\u010cSFD film ID": ["301326"], "PORT film ID": ["152387"], "elFilm film ID": ["1570105"], "Rotten Tomatoes ID": ["m/771417104"], "FilmAffinity ID": ["565716"], "Kinopoisk film ID": ["588604"], "Deutsche Synchronkartei film ID": ["34175"], "Moviepilot.de film ID": ["bbuddah-hoga-terra-baap"], "composer": ["Vishal\u2013Shekhar"], "genre": ["action film"], "Netflix ID": ["70204288"]}, "Q4746547": {"IMDb ID": ["tt0233202"], "instance of": ["film"], "director": ["Mohan Kumar"], "cast member": ["Dev Anand", "Hema Malini", "Prem Nath", "Ranjeet", "Sujit Kumar", "Chaman Puri", "Mohan Choti", "Mehmood Junior", "Sulochana Latkar"], "publication date": [{"time": "+1974-01-01T00:00:00Z", "timezone": 0, "before": 0, "after": 0, "precision": 9, "calendarmodel": "http://www.wikidata.org/entity/Q1985727"}], "original language of film or TV show": ["Hindi"], "country of origin": ["India"], "producer": ["Mohan Kumar"], "Kinopoisk film ID": ["63263"], "composer": ["Laxmikant-Pyarelal"], "\u010cSFD film ID": ["224722"], "elFilm film ID": ["229860"], "Rotten Tomatoes ID": ["m/amir-garib"], "AllMovie movie ID": ["v418701"], "Indiancine.ma film ID": ["QBP"]}, "Q4662781": {"IMDb ID": ["tt0178210"], "instance of": ["film"], "cast member": ["Jeetendra", "Neetu Singh"], "director of photography": ["K. K. Mahajan"], "publication date": [{"time": "+1979-01-01T00:00:00Z", "timezone": 0, "before": 0, "after": 0, "precision": 9, "calendarmodel": "http://www.wikidata.org/entity/Q1985727"}], "original language of film or TV show": ["Hindi"], "country of origin": ["India"], "producer": ["Mohan Kumar"], "composer": ["Ravindra Jain"], "OFDb ID": ["99319"], "Rotten Tomatoes ID": ["m/aatish_1979"], "elFilm film ID": ["176129"], "\u010cSFD film ID": ["55099"], "Kinopoisk film ID": ["134671"], "Indiancine.ma film ID": ["TOP"]}, "Q4662788": {"IMDb ID": ["tt2389974"], "instance of": ["film"], "cast member": ["Bipasha Basu", "Nawazuddin Siddiqui"], "genre": ["psychological thriller", "horror film"], "publication date": [{"time": "+2013-01-01T00:00:00Z", "timezone": 0, "before": 0, "after": 0, "precision": 9, "calendarmodel": "http://www.wikidata.org/entity/Q1985727"}], "country of origin": ["India"], "original language of film or TV show": ["Hindi"], "Kinopoisk film ID": ["710146"], "Freebase ID": ["/m/0r4xmjh"], "OFDb ID": ["258298"], "elCinema film ID": ["2020702"], "MovieMeter film ID": ["93632"], "elFilm film ID": ["1805282"], "\u010cSFD film ID": ["336030"], "AllMovie movie ID": ["v580075"], "Rotten Tomatoes ID": ["m/aatma"], "Sratim ID": ["tt1127645"], "Deutsche Synchronkartei film ID": ["36630"], "Letterboxd film ID": ["aatma-2013"]}}