{"Q6343590": {"IMDb ID": ["tt0156691"], "instance of": ["film"], "director": ["Mahesh Bhatt"], "cast member": ["Jackie Shroff", "Dimple Kapadia", "Anupam Kher"], "original language of film or TV show": ["Hindi"], "producer": ["Anwar Ali"], "director of photography": ["Babubhai Mistry", "Pravin Bhatt"], "publication date": [{"time": "+1987-01-01T00:00:00Z", "timezone": 0, "before": 0, "after": 0, "precision": 9, "calendarmodel": "http://www.wikidata.org/entity/Q1985727"}], "country of origin": ["India"], "composer": ["Rajesh Roshan"], "Kinopoisk film ID": ["36636"], "OFDb ID": ["62810"], "color": ["color"], "elFilm film ID": ["155213"], "\u010cSFD film ID": ["118005"], "PORT film ID": ["111558"], "duration": [{"amount": "+140", "unit": "http://www.wikidata.org/entity/Q7727"}], "screenwriter": ["Mahesh Bhatt"], "Indiancine.ma film ID": ["ABVT"], "genre": ["drama film"]}, "Q6344563": {"IMDb ID": ["tt0156663"], "instance of": ["film"], "director": ["Mahesh Bhatt"], "cast member": ["Sanjay Dutt"], "producer": ["Nanabhai Bhatt"], "publication date": [{"time": "+1988-01-01T00:00:00Z", "timezone": 0, "before": 0, "after": 0, "precision": 9, "calendarmodel": "http://www.wikidata.org/entity/Q1985727"}], "original language of film or TV show": ["Hindi"], "country of origin": ["India"], "composer": ["Rajesh Roshan"], "Kinopoisk film ID": ["39701"], "OFDb ID": ["225444"], "color": ["color"], "elFilm film ID": ["155185"], "\u010cSFD film ID": ["107218"], "Indiancine.ma film ID": ["ACUC"]}, "Q6125790": {"IMDb ID": ["tt0352457"], "instance of": ["film"], "cast member": ["Sandhya Shantaram"], "director": ["V. Shantaram"], "publication date": [{"time": "+1971-01-01T00:00:00Z", "timezone": 0, "before": 0, "after": 0, "precision": 9, "calendarmodel": "http://www.wikidata.org/entity/Q1985727"}], "original language of film or TV show": ["Hindi"], "country of origin": ["India"], "Kinopoisk film ID": ["99439"], "\u010cSFD film ID": ["205212"], "composer": ["Laxmikant-Pyarelal"], "Indiancine.ma film ID": ["OKN"], "Letterboxd film ID": ["jal-bin-machhli-nritya-bin-bijli"]}, "Q6127239": {"instance of": ["film"], "director": ["A. Kodandarami Reddy"], "cast member": ["Hema Malini", "Anil Kapoor", "Madhuri Dixit", "Shakti Kapoor", "Disco Shanti", "Annu Kapoor", "Anupam Kher", "Jagdeep", "Seema Deo", "Satish Kaushik", "Alok Nath", "Vikas Anand", "Shashi Puri"], "original language of film or TV show": ["Hindi"], "publication date": [{"time": "+1990-01-01T00:00:00Z", "timezone": 0, "before": 0, "after": 0, "precision": 9, "calendarmodel": "http://www.wikidata.org/entity/Q1985727"}], "country of origin": ["India"], "color": ["color"], "IMDb ID": ["tt0102148"], "Kinopoisk film ID": ["221880"], "Quora topic ID": ["Jamai-Raja"], "Rotten Tomatoes ID": ["m/jamai-raja"], "\u010cSFD film ID": ["258576"], "elFilm film ID": ["101774"], "composer": ["Laxmikant-Pyarelal"], "Letterboxd film ID": ["jamai-raja"]}}