{"Q15643554": {"instance of": ["film"], "cast member": ["Salman Khan", "Tabu", "Daisy Shah", "Danny Denzongpa", "Sunil Shetty", "Genelia D'Souza Deshmukh"], "publication date": [{"time": "+2014-01-23T00:00:00Z", "timezone": 0, "before": 0, "after": 0, "precision": 11, "calendarmodel": "http://www.wikidata.org/entity/Q1985727"}, {"time": "+2014-01-24T00:00:00Z", "timezone": 0, "before": 0, "after": 0, "precision": 11, "calendarmodel": "http://www.wikidata.org/entity/Q1985727"}], "original language of film or TV show": ["Hindi"], "AlloCin\u00e9 film ID": ["226251"], "country of origin": ["India"], "production company": ["Sohail Khan Productions"], "director": ["Sohail Khan"], "IMDb ID": ["tt1188982"], "producer": ["Sohail Khan"], "distributed by": ["Eros International"], "Kinopoisk film ID": ["406367"], "\u010cSFD film ID": ["248684"], "elCinema film ID": ["2027659"], "elFilm film ID": ["1052372"], "OFDb ID": ["266149"], "MovieMeter film ID": ["97171"], "AllMovie movie ID": ["v593137"], "director of photography": ["Santosh Thundiyil"], "Freebase ID": ["/m/0pdcywh"], "color": ["color"], "based on": ["Stalin"], "Rotten Tomatoes ID": ["m/jai_ho"], "Box Office Mojo film ID": ["jaiho"], "TMDb movie ID": ["244237"], "Moviepilot.de film ID": ["jai-ho"], "genre": ["drama film", "action film"], "composer": ["Sajid-Wajid"], "Indiancine.ma film ID": ["BBVL"], "FilmAffinity ID": ["653995"]}, "Q15643909": {"instance of": ["film"], "country of origin": ["India"], "publication date": [{"time": "+2009-00-00T00:00:00Z", "timezone": 0, "before": 0, "after": 0, "precision": 9, "calendarmodel": "http://www.wikidata.org/entity/Q1985727"}], "original language of film or TV show": ["Hindi"]}, "Q15644769": {"instance of": ["film"], "publication date": [{"time": "+1977-00-00T00:00:00Z", "timezone": 0, "before": 0, "after": 0, "precision": 9, "calendarmodel": "http://www.wikidata.org/entity/Q1985727"}], "country of origin": ["India"], "original language of film or TV show": ["Hindi"], "cast member": ["Neetu Singh"]}, "Q15645905": {"country of origin": ["India"], "instance of": ["film"], "publication date": [{"time": "+2005-01-01T00:00:00Z", "timezone": 0, "before": 0, "after": 0, "precision": 9, "calendarmodel": "http://www.wikidata.org/entity/Q1985727"}], "director": ["Ruchi Narain"], "original language of film or TV show": ["Hindi"], "cast member": ["Chitrangada Singh"], "color": ["color"], "composer": ["Shantanu Moitra"], "IMDb ID": ["tt0461258"], "Indiancine.ma film ID": ["ATXF"]}}