{"Q181795": {"director": ["Irvin Kershner"], "producer": ["Gary Kurtz"], "director of photography": ["Peter Suschitzky"], "production company": ["Lucasfilm"], "part of the series": ["Star Wars", "Star Wars Trilogy"], "IMDb ID": ["tt0080684"], "instance of": ["film"], "screenwriter": ["Leigh Brackett", "Lawrence Kasdan", "George Lucas"], "cast member": ["Harrison Ford", "Carrie Fisher", "David Prowse", "Mark Hamill", "Billy Dee Williams", "Anthony Daniels", "Kenny Baker", "Peter Mayhew", "Alec Guinness", "Denis Lawson", "Jeremy Bulloch", "Julian Glover", "Christopher Malcolm", "John Ratzenberger", "Kenneth Colley", "Michael Sheard", "Marjorie Eaton", "Frank Oz", "Treat Williams", "Ian McDiarmid", "Mark Jones", "John Hollis", "Peter MacDonald", "Jack Purvis", "Clive Revill", "Michael Culver", "John Morton"], "Commons category": ["Star Wars: Episode V \u2013 The Empire Strikes Back"], "soundtrack release": ["Star Wars Episode V: The Empire Strikes Back"], "genre": ["science fiction action film", "adventure film", "action film", "fantasy film"], "official website": ["http://www.starwars.com/explore/the-movies/episode-v"], "topic's main category": ["Category:The Empire Strikes Back"], "Freebase ID": ["/m/0f3m1"], "GND ID": ["4396738-3"], "Library of Congress authority ID": ["n80020079"], "VIAF ID": ["186700474"], "AlloCin\u00e9 film ID": ["25802"], "Rotten Tomatoes ID": ["m/empire_strikes_back"], "publication date": [{"time": "+1980-05-17T00:00:00Z", "timezone": 0, "before": 0, "after": 0, "precision": 11, "calendarmodel": "http://www.wikidata.org/entity/Q1985727"}, {"time": "+1980-05-21T00:00:00Z", "timezone": 0, "before": 0, "after": 0, "precision": 11, "calendarmodel": "http://www.wikidata.org/entity/Q1985727"}, {"time": "+1980-08-15T00:00:00Z", "timezone": 0, "before": 0, "after": 0, "precision": 11, "calendarmodel": "http://www.wikidata.org/entity/Q1985727"}, {"time": "+1980-12-11T00:00:00Z", "timezone": 0, "before": 0, "after": 0, "precision": 11, "calendarmodel": "http://www.wikidata.org/entity/Q1985727"}, {"time": "+1980-08-20T00:00:00Z", "timezone": 0, "before": 0, "after": 0, "precision": 11, "calendarmodel": "http://www.wikidata.org/entity/Q1985727"}], "AllMovie movie ID": ["v15750"], "country of origin": ["United States of America"], "award received": ["National Film Registry", "Academy Award for Best Sound Mixing"], "original language of film or TV show": ["English"], "PORT film ID": ["233"], "composer": ["John Williams"], "DNF film ID": ["10898", "17861"], "Biblioth\u00e8que nationale de France ID": ["14438655w"], "Box Office Mojo film ID": ["starwars5"], "FilmAffinity ID": ["605090"], "film editor": ["Paul Hirsch", "George Lucas", "Marcia Lucas"], "executive producer": ["Gary Kurtz"], "title": [{"text": "Star Wars: Episode V \u2013 The Empire Strikes Back", "language": "en"}], "Metacritic ID": ["movie/star-wars-episode-v---the-empire-strikes-back"], "duration": [{"amount": "+124", "unit": "http://www.wikidata.org/entity/Q7727"}], "color": ["color"], "distributed by": ["InterCom", "Mok\u00e9p", "20th Century Studios"], "nominated for": ["Academy Award for Best Production Design", "Academy Award for Best Original Score", "Academy Award for Best Sound Mixing"], "\u010cSFD film ID": ["5238"], "MovieMeter film ID": ["85"], "KINENOTE film ID": ["4738"], "Allcinema film ID": ["11831"], "Swedish Film Database film ID": ["7900"], "Netflix ID": ["60011114"], "production designer": ["Norman Reynolds"], "Kinopoisk film ID": ["338"], "TCM Movie Database film ID": ["74051"], "film crew member": ["Bob Anderson"], "Elonet movie ID": ["123158"], "ISzDb film ID": ["789"], "cine.gr film ID": ["570"], "costume designer": ["John Mollo"], "LdiF ID": ["32311"], "Open Media Database film ID": ["1891"], "OFDb ID": ["243"], "Scope.dk film ID": ["1525"], "elCinema film ID": ["2019421"], "EDb film ID": ["t0003230"], "elFilm film ID": ["80484"], "takes place in fictional universe": ["Star Wars universe"], "aspect ratio": ["2.35:1"], "AFI Catalog of Feature Films ID": ["56403"], "cost": [{"amount": "+18000000", "unit": "http://www.wikidata.org/entity/Q4917"}], "FSK film rating": ["FSK 12"], "Quora topic ID": ["Star-Wars-Episode-V-The-Empire-Strikes-Back-1980-movie"], "Cinema.de ID": ["1320113"], "Movie Walker film ID": ["mv4729"], "The Numbers movie ID": ["Empire-Strikes-Back-The"], "TV Guide show ID": ["113915"], "Filmweb.pl ID": ["Imperium.Kontratakuje"], "EIDR identifier": ["10.5240/0728-15BC-4706-83CB-7D55-W"], "Deutsche Synchronkartei film ID": ["1602"], "TV.com ID": ["movies/the-empire-strikes-back"], "Sratim ID": ["tt160"], "BFI National Archive work ID": ["150051727"], "voice actor": ["Frank Oz", "Clive Revill", "James Earl Jones", "Jason Wingreen", "Temuera Morrison"], "Cin\u00e9math\u00e8que qu\u00e9b\u00e9coise work identifier": ["1054"], "has quality": ["fails the Bechdel Test"], "Bechdel Test Movie List ID": ["670"], "MYmovies movie ID": ["11675"], "cinematografo film ID": ["16892"], "narrative location": ["Hoth", "Dagobah", "Bespin"], "filming location": ["Finse"], "MPAA film rating": ["PG"], "TMDb movie ID": ["1891"], "Il mondo dei doppiatori ID": ["film/starwars5"], "described at URL": ["http://www.movist.com/movist3d/movie.asp?mid=135"], "Encyclop\u00e6dia Britannica Online ID": ["topic/The-Empire-Strikes-Back"], "Douban film ID": ["1296528"], "The Encyclopedia of Science Fiction ID": ["empire_strikes_back_the", "star_wars_episode_v_the_empire_strikes_back"], "CineMagia film ID": ["1465"], "Fandango film ID": ["40332"], "Moviepilot.de film ID": ["star-wars-episode-v-das-imperium-schlaegt-zurueck"], "Movies Anywhere ID": ["star-wars-the-empire-strikes-back"], "IdRef ID": ["182088855"], "Letterboxd film ID": ["the-empire-strikes-back"], "Siamzone film ID": ["1996"], "has edition": ["A Birodalom visszav\u00e1g"], "Academy Awards Database film ID": ["2324"], "derivative work": ["Star Wars: The Empire Strikes Back", "Star Wars: The Empire Strikes Back", "Star Wars: The Empire Strikes Back", "The Empire Strikes Back"], "box office": [{"amount": "+547879454", "unit": "http://www.wikidata.org/entity/Q4917"}], "Comic Vine ID": ["4025-78"], "Google Play Movies & TV ID": ["Ooh3k8cJDBg"], "Vudu video ID": ["8847"], "MUBI film ID": ["22845"], "logo image": ["Theempirestrikesback-logo2.svg"], "Disney+ movie ID": ["iqtDTZAewwYl"], "Medier\u00e5det rating": ["For ages 12 and up"], "French Vikidia ID": ["Star_Wars,_\u00e9pisode_V_:_L'Empire_contre-attaque"], "exploitation visa number": ["52692"], "CNC film rating (France)": ["no age restriction (U)"], "Cineplex film ID": ["11543"], "FandangoNow ID": ["MMVCCF63891017367FD78CD2B07A78D48FF8"], "Fandom article ID": ["starwars:Star_Wars:_Episode_V_The_Empire_Strikes_Back", "movies:The_Empire_Strikes_Back", "the80smovies:Star_Wars_V:_The_Empire_Strikes_Back"], "Movie Review Query Engine ID": ["star-wars-episode-v-the-empire-strikes-back-m100033252"], "Filmfront film ID": ["180"]}, "Q181803": {"codename": [{"text": "Blue Harvest", "language": "en"}], "director": ["Richard Marquand"], "producer": ["Howard Kazanjian", "Rick McCallum"], "cast member": ["Harrison Ford", "Carrie Fisher", "David Prowse", "Mark Hamill", "Ian McDiarmid", "Billy Dee Williams", "Anthony Daniels", "Kenny Baker", "Peter Mayhew", "Alec Guinness", "Sebastian Shaw", "Denis Lawson", "Jeremy Bulloch", "Femi Taylor", "Caroline Blakiston", "Deep Roy", "Hayden Christensen", "Kenneth Colley", "Warwick Davis", "Michael Pennington", "Mike Quinn", "Frank Oz", "Richard Marquand", "Debbie Lee Carrington", "Paul Brooke", "Tony Cox", "Felix Silla", "Richard Driscoll", "Phil Fondacaro", "Michael Gilden", "Dermot Crowley", "Hilton McRae", "Michael Carter", "Ernie Fosselius", "Timothy M. Rose", "Jack Purvis"], "director of photography": ["Alan Hume", "Alec Mills"], "production company": ["Lucasfilm"], "IMDb ID": ["tt0086190"], "instance of": ["film"], "screenwriter": ["Lawrence Kasdan", "George Lucas"], "Commons category": ["Star Wars: Episode VI \u2013 Return of the Jedi"], "genre": ["science fiction film", "adventure film", "fantasy film", "action film"], "official website": ["http://www.starwars.com/explore/the-movies/episode-vi"], "topic's main category": ["Category:Return of the Jedi"], "Freebase ID": ["/m/0ddjy"], "GND ID": ["4177920-4"], "Library of Congress authority ID": ["n83166250"], "VIAF ID": ["179032366"], "part of the series": ["Star Wars", "Star Wars Trilogy"], "AlloCin\u00e9 film ID": ["25803"], "Rotten Tomatoes ID": ["m/return_of_the_jedi"], "publication date": [{"time": "+1983-05-25T00:00:00Z", "timezone": 0, "before": 0, "after": 0, "precision": 11, "calendarmodel": "http://www.wikidata.org/entity/Q1985727"}, {"time": "+1983-12-09T00:00:00Z", "timezone": 0, "before": 0, "after": 0, "precision": 11, "calendarmodel": "http://www.wikidata.org/entity/Q1985727"}], "AllMovie movie ID": ["v41093"], "country of origin": ["United States of America"], "original language of film or TV show": ["English"], "filming location": ["California", "Arizona", "Jedediah Smith Redwoods State Park"], "PORT film ID": ["10552"], "image": ["Return of the jedi logo.png"], "composer": ["John Williams"], "DNF film ID": ["3849", "17862"], "Biblioth\u00e8que nationale de France ID": ["14438661t"], "Metacritic ID": ["movie/star-wars-episode-vi---return-of-the-jedi"], "Box Office Mojo film ID": ["starwars6"], "executive producer": ["George Lucas"], "film editor": ["Duwayne Dunham", "Marcia Lucas", "George Lucas"], "FilmAffinity ID": ["226172"], "title": [{"text": "Star Wars Episode VI: Return of the Jedi", "language": "en"}], "nominated for": ["Academy Award for Best Sound Editing", "Academy Award for Best Production Design", "Academy Award for Best Original Score", "Academy Award for Best Sound Mixing"], "color": ["color"], "distributed by": ["InterCom", "Mok\u00e9p", "20th Century Studios"], "\u010cSFD film ID": ["6474"], "MovieMeter film ID": ["87"], "KINENOTE film ID": ["4737"], "Allcinema film ID": ["11832"], "Swedish Film Database film ID": ["6279"], "production designer": ["Norman Reynolds"], "Kinopoisk film ID": ["447"], "TCM Movie Database film ID": ["88074"], "duration": [{"amount": "+134", "unit": "http://www.wikidata.org/entity/Q7727"}], "Elonet movie ID": ["131580"], "cine.gr film ID": ["571"], "LdiF ID": ["10137"], "Open Media Database film ID": ["1892"], "OFDb ID": ["244"], "elFilm film ID": ["85957"], "Scope.dk film ID": ["1527"], "takes place in fictional universe": ["Star Wars universe"], "aspect ratio": ["2.35:1"], "logo image": ["Returnofthejedi-logo2.svg"], "AFI Catalog of Feature Films ID": ["58057"], "Cinema.de ID": ["1339869"], "Quora topic ID": ["Star-Wars-Episode-VI-Return-of-the-Jedi-1983-movie"], "Deutsche Synchronkartei film ID": ["2765"], "Movie Walker film ID": ["mv4728"], "TV Guide show ID": ["115820"], "elCinema film ID": ["2019420"], "EDb film ID": ["t0003570"], "Netflix ID": ["60010820"], "The Numbers movie ID": ["Star-Wars-Ep-VI-Return-of-the-Jedi"], "Filmweb.pl ID": ["Powrot.Jedi"], "EIDR identifier": ["10.5240/2BC3-32F8-A5E2-969E-0368-2"], "TV.com ID": ["movies/star-wars-episode-vi-return-of-the-jedi"], "ISAN": ["0000-0000-6A4A-0000-L-0000-0000-B"], "voice actor": ["Frank Oz", "James Earl Jones"], "Cin\u00e9math\u00e8que qu\u00e9b\u00e9coise work identifier": ["6743"], "Encyclop\u00e6dia Britannica Online ID": ["topic/Return-of-the-Jedi"], "has quality": ["fails the Bechdel Test"], "Bechdel Test Movie List ID": ["671"], "CineMagia film ID": ["1466"], "narrative location": ["Tatooine", "Dagobah", "Endor"], "soundtrack release": ["Star Wars Episode VI: Return of the Jedi"], "TMDb movie ID": ["1892"], "Il mondo dei doppiatori ID": ["film/starwars6"], "described at URL": ["http://www.movist.com/movist3d/movie.asp?mid=138"], "Douban film ID": ["1297151"], "The Encyclopedia of Science Fiction ID": ["star_wars_episode_vi_return_of_the_jedi"], "Moviepilot.de film ID": ["star-wars-episode-vi-die-rueckkehr-der-jedi-ritter"], "IdRef ID": ["183868196"], "Siamzone film ID": ["1990"], "Academy Awards Database film ID": ["2108"], "derivative work": ["Return of the Jedi: Death Star Battle", "Star Wars: Return of the Jedi"], "box office": [{"amount": "+475100000", "unit": "http://www.wikidata.org/entity/Q4917"}], "Movies Anywhere ID": ["star-wars-return-of-the-jedi"], "Comic Vine ID": ["4025-79"], "Vudu video ID": ["8849"], "MPAA film rating": ["PG"], "MUBI film ID": ["3474"], "Disney+ movie ID": ["6QGKo5mjDBS8"], "Medier\u00e5det rating": ["For ages 12 and up"], "follows": ["Star Wars Episode V: The Empire Strikes Back"], "French Vikidia ID": ["Star_Wars,_\u00e9pisode_VI_:_Le_Retour_du_Jedi"], "exploitation visa number": ["57801"], "CNC film rating (France)": ["no age restriction (U)"], "Letterboxd film ID": ["return-of-the-jedi"], "FandangoNow ID": ["MMVCED39B7F719F088297C635F5F9A61482B"], "Fandom article ID": ["starwars:Star_Wars:_Episode_VI__Return_of_the_Jedi", "movies:Return_of_the_Jedi", "the80smovies:Star_Wars_VI:_Return_of_the_Jedi"], "Movie Review Query Engine ID": ["star-wars-episode-vi-return-of-the-jedi-m100032937"], "Filmfront film ID": ["183"]}, "Q182218": {"PORT film ID": ["120301"], "instance of": ["3D film", "film"], "director": ["Joss Whedon"], "screenwriter": ["Joss Whedon", "Zak Penn"], "producer": ["Kevin Feige"], "production company": ["Marvel Studios", "Paramount Pictures"], "based on": ["Avengers"], "part of the series": ["Marvel Cinematic Universe", "Avengers film series", "Marvel Cinematic Universe Phase One: Avengers Assembled", "Marvel Cinematic Universe: The Infinity Saga"], "director of photography": ["Seamus McGarvey"], "Commons category": ["The Avengers (2012 film)"], "IMDb ID": ["tt0848228"], "soundtrack release": ["The Avengers"], "original language of film or TV show": ["English"], "cast member": ["Don Cheadle", "Jillian Morgese", "Robert Downey, Jr.", "Chris Evans", "Mark Ruffalo", "Chris Hemsworth", "Scarlett Johansson", "Jeremy Renner", "Tom Hiddleston", "Clark Gregg", "Cobie Smulders", "Stellan Skarsg\u00e5rd", "Samuel L. Jackson", "Gwyneth Paltrow", "Alexis Denisof", "Tina Benko", "Jerzy Skolimowski", "Kirill Nikiforov", "Jeff Wolfe", "M'laah Kaur Singh", "Rashmi Rustagi", "Powers Boothe", "Jenny Agutter", "Arthur Darbinyan", "Donald Li", "Warren Kole", "Alicia Sixtos", "Jesse Garcia", "Maximiliano Hern\u00e1ndez", "Dieter Riesle", "Kenneth Tigar", "Walter Perez", "Harry Dean Stanton", "Josh Cowdery", "Ashley Johnson", "Katsumi Komatsu", "Yumiko Komatsu", "Momoko Komatsu", "Robert Clohessy", "Enver Gjokaj", "Fernanda Toker", "Andrea Vecchio", "Robin Swoboda", "Brent McGee", "Jamie McShane", "Michael Zhang", "William Christopher Stephens", "Kelley Robins", "Romy Rosemont", "James Eckhouse", "Stan Lee", "Pat Kiernan", "Thomas Roberts", "Damion Poitier"], "FilmAffinity ID": ["353018"], "genre": ["action film", "science fiction film", "fictional crossover", "superhero film", "speculative fiction film", "adventure film"], "narrative location": ["New York City", "Kolkata"], "official website": ["https://www.marvel.com/movies/the-avengers"], "Freebase ID": ["/m/062zm5h"], "GND ID": ["1042670072"], "AlloCin\u00e9 film ID": ["130440"], "Rotten Tomatoes ID": ["m/marvels_the_avengers"], "Box Office Mojo film ID": ["avengers11"], "publication date": [{"time": "+2012-05-04T00:00:00Z", "timezone": 0, "before": 0, "after": 0, "precision": 11, "calendarmodel": "http://www.wikidata.org/entity/Q1985727"}, {"time": "+2011-07-15T00:00:00Z", "timezone": 0, "before": 0, "after": 0, "precision": 11, "calendarmodel": "http://www.wikidata.org/entity/Q1985727"}, {"time": "+2012-04-27T00:00:00Z", "timezone": 0, "before": 0, "after": 0, "precision": 11, "calendarmodel": "http://www.wikidata.org/entity/Q1985727"}, {"time": "+2012-04-26T00:00:00Z", "timezone": 0, "before": 0, "after": 0, "precision": 11, "calendarmodel": "http://www.wikidata.org/entity/Q1985727"}, {"time": "+2012-04-25T00:00:00Z", "timezone": 0, "before": 0, "after": 0, "precision": 11, "calendarmodel": "http://www.wikidata.org/entity/Q1985727"}], "VIAF ID": ["233291779"], "main subject": ["alien invasion"], "country of origin": ["United States of America"], "AllMovie movie ID": ["v451151"], "filming location": ["Long Island", "New York City", "Los Angeles", "New Mexico", "Pittsburgh"], "DNF film ID": ["77020"], "MovieMeter film ID": ["78348"], "MPAA film rating": ["PG-13"], "composer": ["Alan Silvestri"], "Metacritic ID": ["movie/the-avengers-2012"], "NMHH film rating": ["Category III"], "title": [{"text": "The Avengers", "language": "en"}], "color": ["color"], "Scope.dk film ID": ["8157"], "distributed by": ["F\u00f3rum Hungary", "Paramount Pictures"], "\u010cSFD film ID": ["241997"], "Allcinema film ID": ["341611"], "nominated for": ["Academy Award for Best Visual Effects"], "significant event": ["principal photography", "premi\u00e8re"], "FSK film rating": ["FSK 12"], "BBFC rating": ["12 certificate"], "Kijkwijzer rating": ["12"], "duration": [{"amount": "+142", "unit": "http://www.wikidata.org/entity/Q7727"}], "exploitation visa number": ["133167"], "CNC film rating (France)": ["no age restriction (U)"], "executive producer": ["Jon Favreau", "Stan Lee"], "attendance": [{"amount": "+2393746", "unit": "1"}], "Library of Congress authority ID": ["no2012044014"], "Kinopoisk film ID": ["263531"], "LdiF ID": ["539832"], "ISzDb film ID": ["10012"], "Open Media Database film ID": ["36891"], "OFDb ID": ["225288"], "Elonet movie ID": ["1518653"], "elCinema film ID": ["2004200"], "Swedish Film Database film ID": ["75578"], "elFilm film ID": ["795349"], "TCM Movie Database film ID": ["823683"], "Sratim ID": ["tt149786"], "cine.gr film ID": ["714564"], "EDb film ID": ["t0026754"], "aspect ratio": ["1.85:1"], "costume designer": ["Alexandra Byrne"], "AFI Catalog of Feature Films ID": ["68562"], "TV.com ID": ["movies/marvels-the-avengers"], "JMK film rating": ["free from 12 years"], "codename": [{"text": "Group Hug", "language": "en"}], "takes place in fictional universe": ["Marvel Cinematic Universe"], "Quora topic ID": ["Marvels-The-Avengers-2012-movie"], "cost": [{"amount": "+220000000", "unit": "http://www.wikidata.org/entity/Q4917"}], "box office": [{"amount": "+1518812988", "unit": "http://www.wikidata.org/entity/Q4917"}, {"amount": "+623357910", "unit": "http://www.wikidata.org/entity/Q4917"}], "Movie Walker film ID": ["mv48548"], "Cinema.de ID": ["4265302"], "Deutsche Synchronkartei film ID": ["22221"], "Netflix ID": ["70217913"], "KINENOTE film ID": ["54324"], "EIDR identifier": ["10.5240/EBF7-E7FC-0630-DEE9-94EF-E"], "Cineplex film ID": ["243923"], "The Numbers movie ID": ["Avengers-The-(2011)"], "BBC Things ID": ["866495f8-b1b1-43a1-980b-0e0889dfe631"], "Cin\u00e9math\u00e8que qu\u00e9b\u00e9coise work identifier": ["99353"], "has quality": ["fails the Bechdel Test"], "Bechdel Test Movie List ID": ["3205"], "cinematografo film ID": ["53840"], "TMDb movie ID": ["24428"], "Filmweb.pl film ID": ["371515"], "Il mondo dei doppiatori ID": ["film1/theavengers"], "Douban film ID": ["1866479"], "described at URL": ["http://tw.movie.yahoo.com/movieinfo_main.html/id=4034"], "film editor": ["Jeffrey Ford"], "The Encyclopedia of Science Fiction ID": ["avengers_the_film"], "Cin\u00e9-Ressources film ID": ["116038"], "Moviepilot.de film ID": ["the-avengers"], "Siamzone film ID": ["6391"], "Disney A to Z ID": ["avengers-marvels-the-film"], "Academy Awards Database film ID": ["4554"], "Movies Anywhere ID": ["marvels-the-avengers"], "MusicBrainz work ID": ["75b3d0c4-4b74-4e65-8652-ca10b0a4024a"], "characters": ["Thanos", "Tony Stark", "Phil Coulson"], "TV Tropes identifier": ["Film/TheAvengers2012"], "Comic Vine ID": ["4025-936"], "voice actor": ["Lou Ferrigno", "Paul Bettany"], "logo image": ["The Avengers Logo Black.svg"], "Google Play Movies & TV ID": ["W9ZnpIGvZUo"], "award received": ["MTV Movie Award for Best Villain"], "AMPAS collections film ID": ["1052293"], "Medier\u00e5det rating": ["For ages 11 and up"], "Disney+ movie ID": ["2h6PcHFDbsPy"], "ICAA rating": ["Not recommended for children under 7"], "ICAA film catalogue ID": ["234511"], "ClassInd category": ["12"], "CNC film rating (Romania)": ["A.P. - 12"], "follows": ["Captain America: The First Avenger"], "followed by": ["Iron Man 3"], "RTC film rating": ["B"], "INCAA film rating": ["+13"], "FPB rating": ["10"], "Letterboxd film ID": ["the-avengers-2012"], "FandangoNow ID": ["MMVC4626D19072C7CE5C94653F16372458C7"]}, "Q260379": {"instance of": ["film"], "director": ["Zhang Yimou"], "cast member": ["Jet Li", "Tony Leung", "Maggie Cheung", "Chen Daoming", "Zhang Ziyi", "Donnie Yen"], "IMDb ID": ["tt0299977"], "original language of film or TV show": ["Mandarin Chinese"], "screenwriter": ["Zhang Yimou"], "producer": ["Zhang Yimou"], "director of photography": ["Christopher Doyle"], "official website": ["http://www.miramax.com/movie/hero"], "Freebase ID": ["/m/01v5rj"], "GND ID": ["7701932-5"], "AlloCin\u00e9 film ID": ["47263"], "Rotten Tomatoes ID": ["m/hero"], "publication date": [{"time": "+2002-01-01T00:00:00Z", "timezone": 0, "before": 0, "after": 0, "precision": 9, "calendarmodel": "http://www.wikidata.org/entity/Q1985727"}, {"time": "+2003-06-05T00:00:00Z", "timezone": 0, "before": 0, "after": 0, "precision": 11, "calendarmodel": "http://www.wikidata.org/entity/Q1985727"}], "VIAF ID": ["217950562"], "genre": ["martial arts film", "action film", "fantasy film", "drama film"], "country of origin": ["People's Republic of China"], "AllMovie movie ID": ["v267633"], "PORT film ID": ["57593"], "Metacritic ID": ["movie/hero"], "DNF film ID": ["36991"], "Box Office Mojo film ID": ["hero02"], "title": [{"text": "\u82f1\u96c4", "language": "zh-hant"}], "composer": ["Tan Dun"], "distributed by": ["InterCom"], "nominated for": ["Academy Award for Best Foreign Language Film"], "\u010cSFD film ID": ["38117"], "FSK film rating": ["FSK 12"], "KINENOTE film ID": ["34300"], "Allcinema film ID": ["240359"], "Netflix ID": ["60027142"], "duration": [{"amount": "+99", "unit": "http://www.wikidata.org/entity/Q7727"}], "HKMDB film ID": ["10196"], "Kinopoisk film ID": ["889"], "LdiF ID": ["520460"], "Open Media Database film ID": ["79"], "OFDb ID": ["30573"], "MovieMeter film ID": ["7949"], "elFilm film ID": ["295729"], "cine.gr film ID": ["702725"], "Elonet movie ID": ["1109021"], "Scope.dk film ID": ["1893"], "Swedish Film Database film ID": ["53365"], "color": ["color"], "costume designer": ["Emi Wada"], "FilmAffinity ID": ["158116"], "elCinema film ID": ["2012163"], "EDb film ID": ["t0009313"], "Cinema.de ID": ["1313469"], "Deutsche Synchronkartei film ID": ["10569"], "Filmweb.pl ID": ["Hero"], "EIDR identifier": ["10.5240/15B6-BD3B-FFFE-1D7B-E423-M"], "TV.com ID": ["movies/hero-2004"], "TV Guide show ID": ["136556"], "The Numbers movie ID": ["Jet-Lis-Hero"], "Movie Walker film ID": ["mv33371"], "ISAN": ["0000-0000-ED0F-0000-0-0000-0000-3"], "Encyclop\u00e6dia Britannica Online ID": ["topic/Hero-film-by-Zhang"], "Douban film ID": ["1306123"], "has quality": ["passes the Bechdel Test"], "Bechdel Test Movie List ID": ["732"], "Filmiroda rating": ["Category II"], "Il mondo dei doppiatori ID": ["film/hero"], "TMDb movie ID": ["79"], "production company": ["Sil-Metropole Organisation"], "Moviepilot.de film ID": ["hero"], "Biblioth\u00e8que nationale de France ID": ["16576239b"], "Siamzone film ID": ["1050"], "Academy Awards Database film ID": ["3584"], "narrative location": ["Shaanxi"], "Library of Congress authority ID": ["nr2004000799"], "Google Play Movies & TV ID": ["SQTOI8H8axo"], "Medier\u00e5det rating": ["For ages 11 and up"], "Larousse ID": ["film/wd/95"], "Cin\u00e9math\u00e8que qu\u00e9b\u00e9coise work identifier": ["68163"], "exploitation visa number": ["108868"], "CNC film rating (France)": ["no age restriction (U)"]}}