{"Q6402285": {"IMDb ID": ["tt0076259"], "instance of": ["film"], "director": ["Prakash Mehra"], "cast member": ["Amitabh Bachchan", "Vinod Khanna", "Rekha", "Nirupa Roy", "Asrani", "Aruna Irani", "Kader Khan", "Ranjeet"], "original language of film or TV show": ["Hindi"], "publication date": [{"time": "+1977-01-01T00:00:00Z", "timezone": 0, "before": 0, "after": 0, "precision": 9, "calendarmodel": "http://www.wikidata.org/entity/Q1985727"}], "country of origin": ["India"], "screenwriter": ["Kader Khan"], "Kinopoisk film ID": ["78547"], "director of photography": ["Ishan Arya"], "OFDb ID": ["240660"], "elFilm film ID": ["76080"], "Rotten Tomatoes ID": ["m/khoon_pasina"], "\u010cSFD film ID": ["182561"], "Indiancine.ma film ID": ["SIR"], "composer": ["Kalyanji\u2013Anandji"], "Letterboxd film ID": ["khoon-pasina"]}, "Q6402614": {"IMDb ID": ["tt0155805"], "instance of": ["film"], "cast member": ["Feroz Khan", "Danny Denzongpa"], "original language of film or TV show": ["Hindi"], "publication date": [{"time": "+1973-01-01T00:00:00Z", "timezone": 0, "before": 0, "after": 0, "precision": 9, "calendarmodel": "http://www.wikidata.org/entity/Q1985727"}], "genre": ["Western film", "crime film"], "director": ["Narendra Bedi"], "country of origin": ["India"], "composer": ["Rahul Dev Burman"], "Kinopoisk film ID": ["225740"], "screenwriter": ["Narendra Bedi"], "elFilm film ID": ["154340"], "\u010cSFD film ID": ["266709"], "Rotten Tomatoes ID": ["m/khhotte_sikkay"]}, "Q6402700": {"instance of": ["film"], "director": ["Sudhir Mishra"], "cast member": ["Shiney Ahuja", "Soha Ali Khan", "Rajat Kapoor", "Sushmita Mukherjee"], "MusicBrainz release group ID": ["a954412d-f18c-41d6-9ad8-80e0d60b241f"], "producer": ["Prakash Jha"], "publication date": [{"time": "+2007-01-01T00:00:00Z", "timezone": 0, "before": 0, "after": 0, "precision": 9, "calendarmodel": "http://www.wikidata.org/entity/Q1985727"}], "original language of film or TV show": ["Hindi"], "IMDb ID": ["tt0995823"], "country of origin": ["India"], "composer": ["Shantanu Moitra"], "screenwriter": ["Sudhir Mishra"], "Kinopoisk film ID": ["392436"], "OFDb ID": ["263281"], "color": ["color"], "\u010cSFD film ID": ["231512"], "Rotten Tomatoes ID": ["m/khoya_khoya_chand_2007"], "MovieMeter film ID": ["49130"], "elFilm film ID": ["913804"], "AllMovie movie ID": ["v409356"], "PORT film ID": ["95593"], "Indiancine.ma film ID": ["AVEY"]}, "Q6402798": {"instance of": ["film"], "cast member": ["Sunny Deol", "Tabu", "Farida Jalal", "Govind Namdev", "Ashish Vidyarthi", "Mukesh Rishi", "Daisy Bopanna"], "original language of film or TV show": ["Hindi"], "director": ["K. C. Bokadia"], "publication date": [{"time": "+2010-01-01T00:00:00Z", "timezone": 0, "before": 0, "after": 0, "precision": 9, "calendarmodel": "http://www.wikidata.org/entity/Q1985727"}], "country of origin": ["India"], "color": ["color"], "IMDb ID": ["tt1920986"], "screenwriter": ["K. C. Bokadia"], "composer": ["Aadesh Shrivastava"], "Indiancine.ma film ID": ["AXQW"], "genre": ["action film"]}}