{"Q19842746": {"IMDb ID": ["tt3949660"], "instance of": ["3D film", "film"], "country of origin": ["United States of America"], "director": ["Dave Green"], "FilmAffinity ID": ["621747"], "Box Office Mojo film ID": ["tmnt2016"], "publication date": [{"time": "+2016-06-03T00:00:00Z", "timezone": 0, "before": 0, "after": 0, "precision": 11, "calendarmodel": "http://www.wikidata.org/entity/Q1985727"}, {"time": "+2016-08-11T00:00:00Z", "timezone": 0, "before": 0, "after": 0, "precision": 11, "calendarmodel": "http://www.wikidata.org/entity/Q1985727"}, {"time": "+2016-06-03T00:00:00Z", "timezone": 0, "before": 0, "after": 0, "precision": 11, "calendarmodel": "http://www.wikidata.org/entity/Q1985727"}, {"time": "+2016-05-22T00:00:00Z", "timezone": 0, "before": 0, "after": 0, "precision": 11, "calendarmodel": "http://www.wikidata.org/entity/Q1985727"}, {"time": "+2016-05-29T00:00:00Z", "timezone": 0, "before": 0, "after": 0, "precision": 11, "calendarmodel": "http://www.wikidata.org/entity/Q1985727"}, {"time": "+2016-05-30T00:00:00Z", "timezone": 0, "before": 0, "after": 0, "precision": 11, "calendarmodel": "http://www.wikidata.org/entity/Q1985727"}, {"time": "+2016-06-01T00:00:00Z", "timezone": 0, "before": 0, "after": 0, "precision": 11, "calendarmodel": "http://www.wikidata.org/entity/Q1985727"}, {"time": "+2016-06-02T00:00:00Z", "timezone": 0, "before": 0, "after": 0, "precision": 11, "calendarmodel": "http://www.wikidata.org/entity/Q1985727"}, {"time": "+2016-06-03T00:00:00Z", "timezone": 0, "before": 0, "after": 0, "precision": 11, "calendarmodel": "http://www.wikidata.org/entity/Q1985727"}, {"time": "+2016-06-09T00:00:00Z", "timezone": 0, "before": 0, "after": 0, "precision": 11, "calendarmodel": "http://www.wikidata.org/entity/Q1985727"}, {"time": "+2016-06-10T00:00:00Z", "timezone": 0, "before": 0, "after": 0, "precision": 11, "calendarmodel": "http://www.wikidata.org/entity/Q1985727"}, {"time": "+2016-06-16T00:00:00Z", "timezone": 0, "before": 0, "after": 0, "precision": 11, "calendarmodel": "http://www.wikidata.org/entity/Q1985727"}, {"time": "+2016-06-17T00:00:00Z", "timezone": 0, "before": 0, "after": 0, "precision": 11, "calendarmodel": "http://www.wikidata.org/entity/Q1985727"}, {"time": "+2016-06-23T00:00:00Z", "timezone": 0, "before": 0, "after": 0, "precision": 11, "calendarmodel": "http://www.wikidata.org/entity/Q1985727"}, {"time": "+2016-06-29T00:00:00Z", "timezone": 0, "before": 0, "after": 0, "precision": 11, "calendarmodel": "http://www.wikidata.org/entity/Q1985727"}, {"time": "+2016-06-30T00:00:00Z", "timezone": 0, "before": 0, "after": 0, "precision": 11, "calendarmodel": "http://www.wikidata.org/entity/Q1985727"}, {"time": "+2016-07-02T00:00:00Z", "timezone": 0, "before": 0, "after": 0, "precision": 11, "calendarmodel": "http://www.wikidata.org/entity/Q1985727"}, {"time": "+2016-07-05T00:00:00Z", "timezone": 0, "before": 0, "after": 0, "precision": 11, "calendarmodel": "http://www.wikidata.org/entity/Q1985727"}, {"time": "+2016-07-07T00:00:00Z", "timezone": 0, "before": 0, "after": 0, "precision": 11, "calendarmodel": "http://www.wikidata.org/entity/Q1985727"}, {"time": "+2016-07-21T00:00:00Z", "timezone": 0, "before": 0, "after": 0, "precision": 11, "calendarmodel": "http://www.wikidata.org/entity/Q1985727"}, {"time": "+2016-08-11T00:00:00Z", "timezone": 0, "before": 0, "after": 0, "precision": 11, "calendarmodel": "http://www.wikidata.org/entity/Q1985727"}, {"time": "+2016-08-26T00:00:00Z", "timezone": 0, "before": 0, "after": 0, "precision": 11, "calendarmodel": "http://www.wikidata.org/entity/Q1985727"}], "title": [{"text": "Teenage Mutant Ninja Turtles: Half Shell", "language": "en"}], "filming location": ["New York City", "Foz do Igua\u00e7u"], "Metacritic ID": ["movie/teenage-mutant-ninja-turtles-2"], "cast member": ["Megan Fox", "Stephen Amell", "Will Arnett", "Brian Tee", "Tyler Perry", "Laura Linney", "Brittany Ishibashi", "Pete Ploszek", "Alan Ritchson", "Noel Fisher", "Jeremy Howard", "Danny Woodburn", "Gary Anthony Williams", "Sheamus (the best)", "Brad Garrett", "Robert Clohessy", "Alessandra Ambrosio", "Judith Hoag", "Carmelo Anthony", "DeAndre Jordan", "J. J. Redick", "Austin Rivers", "Matt Barnes", "Spencer Hawes"], "genre": ["martial arts film", "science fiction film", "action film", "comedy film"], "composer": ["Steve Jablonsky"], "Rotten Tomatoes ID": ["m/teenage_mutant_ninja_turtles_out_of_the_shadows"], "AllMovie movie ID": ["v621790"], "AlloCin\u00e9 film ID": ["230822"], "screenwriter": ["Josh Appelbaum"], "production company": ["Paramount Pictures"], "official website": ["http://www.teenagemutantninjaturtlesmovie.com/"], "NMHH film rating": ["Category III"], "Kinopolis film ID": ["96454000012PLXMQDD"], "director of photography": ["Lula Carvalho"], "distributed by": ["Paramount Pictures", "UIP-Dunafilm"], "Cineplex film ID": ["325085"], "narrative location": ["New York City", "Manaus", "Technodrome"], "main subject": ["alien invasion"], "Kinopoisk film ID": ["841518"], "Kijkwijzer rating": ["12"], "MPAA film rating": ["PG-13"], "MovieMeter film ID": ["284094"], "Swedish Film Database film ID": ["83238"], "\u010cSFD film ID": ["389063"], "OFDb ID": ["287974"], "PORT film ID": ["171482"], "elFilm film ID": ["1812386"], "Scope.dk film ID": ["10703", "10627"], "elCinema film ID": ["2041528"], "Elonet movie ID": ["1576045"], "DNF film ID": ["96262"], "cine.gr film ID": ["721617"], "Facebook ID": ["TMNT"], "Twitter username": ["TMNTmovie"], "Instagram username": ["tmntmovie"], "producer": ["Michael Bay"], "ClassInd category": ["10"], "Google Knowledge Graph ID": ["/g/11b67yc985"], "ICAA rating": ["Not recommended for children under 7"], "Open Media Database film ID": ["95854"], "color": ["color"], "CNC film rating (Romania)": ["A.P. - 12"], "EIRIN film rating": ["G"], "film editor": ["Bob Ducsay"], "RARS rating": ["6+"], "Minkultury film ID": ["181395524"], "CNC film rating (France)": ["no age restriction (U)"], "exploitation visa number": ["144466"], "JMK film rating": ["free from 8 years"], "FSK film rating": ["FSK 12"], "RTC film rating": ["B"], "Giphy username": ["tmntmovie"], "duration": [{"amount": "+112", "unit": "http://www.wikidata.org/entity/Q7727"}], "Deutsche Synchronkartei film ID": ["34556"], "part of the series": ["Teenage Mutant Ninja Turtles"], "characters": ["Donatello", "Leonardo", "Michelangelo", "Raphael", "Splinter", "April O'Neil", "Casey Jones", "Baxter Stockman", "Karai", "Shredder", "Bebop", "Owen Rocksteed", "Krang", "Eric Sacks"], "original language of film or TV show": ["English"], "Commons category": ["Teenage Mutant Ninja Turtles: Out of the Shadows"], "Netflix ID": ["80092423"], "Quora topic ID": ["Teenage-Mutant-Ninja-Turtles-Out-of-the-Shadows-2016-movie"], "has quality": ["passes the Bechdel Test"], "Bechdel Test Movie List ID": ["6915"], "Movieplayer film ID": ["41157"], "Douban film ID": ["25955779"], "TMDb movie ID": ["308531"], "costume designer": ["Sarah Edwards", "Sarah Edwards"], "based on": ["Teenage Mutant Ninja Turtles"], "box office": [{"amount": "+245600000", "unit": "http://www.wikidata.org/entity/Q4917"}], "Filmweb.pl film ID": ["720565"], "Comic Vine ID": ["4025-2157"], "logo image": ["TMNT Out of the Shadows logo.png"], "Medier\u00e5det rating": ["For ages 11 and up"], "FPB rating": ["10-12 PG"], "BBFC rating": ["12 certificate"], "ICAA film catalogue ID": ["153015"], "INCAA film rating": ["+13"], "Google Play Movies & TV ID": ["vx1r7CEVl5k"], "takes place in fictional universe": ["Teenage Mutant Ninja Turtles universe"], "Fandom article ID": ["turtlepedia:Teenage_Mutant_Ninja_Turtles:_Out_of_the_Shadows_(film)", "movies:Teenage_Mutant_Ninja_Turtles:_Out_of_the_Shadows", "culture:Teenage_Mutant_Ninja_Turtles:_Out_of_the_Shadows", "logos:Teenage_Mutant_Ninja_Turtles:_Out_of_the_Shadows_(film)", "platinumdunes:Teenage_Mutant_Ninja_Turtles:_Out_of_the_Shadows", "paramount-teenage-mutant-ninja-turtles:Teenage_Mutant_Ninja_Turtles:_Out_of_the_Shadows", "scifi:Teenage_Mutant_Ninja_Turtles:_Out_of_the_Shadows"], "Classification RCQ": ["G"], "Moviepilot.de film ID": ["teenage-mutant-ninja-turtles-2-out-of-the-shadows"], "Letterboxd film ID": ["teenage-mutant-ninja-turtles-out-of-the-shadows"], "FandangoNow ID": ["MMV48094C7290D8649E722E87BF507F491BA"]}, "Q19844592": {"instance of": ["film"], "cast member": ["Paresh Rawal", "Akshay Kumar", "John Abraham"], "original language of film or TV show": ["English"], "country of origin": ["India"], "composer": ["Anu Malik"], "publication date": [{"time": "+2015-12-18T00:00:00Z", "timezone": 0, "before": 0, "after": 0, "precision": 11, "calendarmodel": "http://www.wikidata.org/entity/Q1985727"}], "director": ["Neeraj Vora"], "title": [{"text": "Hera Pheri 3", "language": "en"}], "IMDb ID": ["tt4907960"]}, "Q19672485": {"country of origin": ["Nepal"], "instance of": ["film"]}, "Q20001199": {"instance of": ["3D film", "film"], "IMDb ID": ["tt3896198"], "publication date": [{"time": "+2017-05-05T00:00:00Z", "timezone": 0, "before": 0, "after": 0, "precision": 11, "calendarmodel": "http://www.wikidata.org/entity/Q1985727"}, {"time": "+2017-04-28T00:00:00Z", "timezone": 0, "before": 0, "after": 0, "precision": 11, "calendarmodel": "http://www.wikidata.org/entity/Q1985727"}, {"time": "+2017-04-10T00:00:00Z", "timezone": 0, "before": 0, "after": 0, "precision": 11, "calendarmodel": "http://www.wikidata.org/entity/Q1985727"}, {"time": "+2017-04-27T00:00:00Z", "timezone": 0, "before": 0, "after": 0, "precision": 11, "calendarmodel": "http://www.wikidata.org/entity/Q1985727"}, {"time": "+2017-04-19T00:00:00Z", "timezone": 0, "before": 0, "after": 0, "precision": 11, "calendarmodel": "http://www.wikidata.org/entity/Q1985727"}, {"time": "+2017-04-25T00:00:00Z", "timezone": 0, "before": 0, "after": 0, "precision": 11, "calendarmodel": "http://www.wikidata.org/entity/Q1985727"}, {"time": "+2017-05-03T00:00:00Z", "timezone": 0, "before": 0, "after": 0, "precision": 11, "calendarmodel": "http://www.wikidata.org/entity/Q1985727"}, {"time": "+2017-04-25T00:00:00Z", "timezone": 0, "before": 0, "after": 0, "precision": 11, "calendarmodel": "http://www.wikidata.org/entity/Q1985727"}, {"time": "+2017-04-26T00:00:00Z", "timezone": 0, "before": 0, "after": 0, "precision": 11, "calendarmodel": "http://www.wikidata.org/entity/Q1985727"}, {"time": "+2017-05-12T00:00:00Z", "timezone": 0, "before": 0, "after": 0, "precision": 11, "calendarmodel": "http://www.wikidata.org/entity/Q1985727"}, {"time": "+2017-05-04T00:00:00Z", "timezone": 0, "before": 0, "after": 0, "precision": 11, "calendarmodel": "http://www.wikidata.org/entity/Q1985727"}], "director": ["James Gunn"], "color": ["color"], "screenwriter": ["James Gunn"], "original language of film or TV show": ["English"], "producer": ["Kevin Feige"], "based on": ["Guardians of the Galaxy"], "country of origin": ["United States of America"], "part of the series": ["Marvel Cinematic Universe", "Guardians of the Galaxy film series", "Marvel Cinematic Universe Phase Three", "Marvel Cinematic Universe: The Infinity Saga"], "cast member": ["Chris Pratt", "Zoe Saldana", "Dave Bautista", "Michael Rooker", "Karen Gillan", "Sean Gunn", "Pom Klementieff", "Steve Agee", "Glenn Close", "Kurt Russell", "Elizabeth Debicki", "Chris Sullivan", "Tommy Flanagan", "Evan Jones", "James Euringer", "Stephen Blackehart", "Joe Fria", "Terence Rosemore", "Mike Escamilla", "Don Johnson", "Sylvester Stallone", "Stan Lee", "Rhoda Griffis", "Gregg Henry", "Ving Rhames", "Michael Rosenbaum", "Michelle Yeoh", "David Hasselhoff", "Rob Zombie", "Jeff Goldblum", "Laura Haddock", "Aaron Schwartz", "Hannah Harlow", "Hilty Bowen", "Ben Browder", "Alex Klein", "Luke Cook", "Blondy Baruti", "Richard Christy", "Sierra Love", "Kendra Carelli", "Milynn Sarley", "Molly Quinn", "Mac Wells", "James Gunn Sr.", "Leota Gunn", "Elizabeth Ludlow", "Wyatt Oleff", "Damita Jane Howard"], "genre": ["superhero film", "action film", "adventure film", "science fiction film", "comedy film"], "composer": ["Tyler Bates"], "title": [{"text": "Guardians of the Galaxy Vol. 2", "language": "en"}], "production company": ["Marvel Studios"], "Rotten Tomatoes ID": ["m/guardians_of_the_galaxy_2"], "Box Office Mojo film ID": ["marvel17a"], "Metacritic ID": ["movie/guardians-of-the-galaxy-vol-2"], "AlloCin\u00e9 film ID": ["226995"], "filming location": ["Pinewood Atlanta Studios"], "AllMovie movie ID": ["v609066"], "significant event": ["principal photography", "premi\u00e8re"], "director of photography": ["Henry Braham"], "executive producer": ["Louis D'Esposito", "Victoria Alonso", "Jonathan Schwartz", "Nik Korda", "Stan Lee"], "production designer": ["Scott Chambliss"], "film editor": ["Fred Raskin", "Craig Wood"], "costume designer": ["Judianna Makovsky"], "distributed by": ["Walt Disney Studios Motion Pictures"], "Commons category": ["Guardians of the Galaxy Vol. 2"], "Kinopoisk film ID": ["841263"], "elFilm film ID": ["1812374"], "\u010cSFD film ID": ["380161"], "elCinema film ID": ["2032788"], "Freebase ID": ["/m/011cjkjg"], "has quality": ["teaser trailer", "passes the Bechdel Test"], "PORT film ID": ["175228"], "FilmAffinity ID": ["406284"], "codename": [{"text": "Level Up", "language": "en"}], "MPAA film rating": ["PG-13"], "KMRB film rating": ["12"], "takes place in fictional universe": ["Marvel Cinematic Universe"], "Cineplex film ID": ["320440"], "BBFC rating": ["12A certificate"], "ClassInd category": ["12"], "RTC film rating": ["B"], "NMHH film rating": ["Category III"], "CNC film rating (France)": ["no age restriction (U)"], "exploitation visa number": ["146428"], "duration": [{"amount": "+136", "unit": "http://www.wikidata.org/entity/Q7727"}], "DNF film ID": ["97806"], "INCAA film rating": ["+13"], "soundtrack release": ["Guardians of the Galaxy Vol. 2"], "review score": ["7.9/10", "67/100", "81%"], "ICAA rating": ["not recommended for children under 12"], "cost": [{"amount": "+200000000", "unit": "http://www.wikidata.org/entity/Q4917"}], "box office": [{"amount": "+863756051", "unit": "http://www.wikidata.org/entity/Q4917"}], "official website": ["http://movies.disney.com/guardians-of-the-galaxy-vol-2"], "Elonet movie ID": ["1582951"], "CNC film rating (Romania)": ["A.P. - 12"], "Swedish Film Database film ID": ["88778"], "Scope.dk film ID": ["11142"], "FSK film rating": ["FSK 12"], "Instagram username": ["guardiansofthegalaxy"], "Twitter username": ["Guardians"], "Facebook ID": ["guardiansofthegalaxy"], "Kijkwijzer rating": ["12"], "fabrication method": ["rendering"], "item operated": ["Arnold"], "ISAN": ["0000-0004-926A-0000-U-0000-0000-L"], "VIAF ID": ["373149294499880522098"], "Library of Congress authority ID": ["no2017049427"], "logo image": ["Guardians of the Galaxy Vol 2 Logo Black.svg"], "Bechdel Test Movie List ID": ["7595"], "CineMagia film ID": ["591443"], "Deutsche Synchronkartei film ID": ["37269"], "TMDb movie ID": ["283995"], "Netflix ID": ["80156386"], "Il mondo dei doppiatori ID": ["film1/guardianidellagalassia2"], "ICAA film catalogue ID": ["184716"], "Douban film ID": ["25937854"], "described at URL": ["http://app2.atmovies.com.tw/film/fgen53896198"], "The Encyclopedia of Science Fiction ID": ["guardians_of_the_galaxy_vol_2"], "Cin\u00e9-Ressources film ID": ["135306"], "aspect ratio": ["2.39:1", "19:10"], "Moviepilot.de film ID": ["guardians-of-the-galaxy-2"], "TV.com ID": ["movies/guardians-of-the-galaxy-vol-2"], "Filmweb.pl film ID": ["722146"], "cine.gr film ID": ["722544"], "Allcinema film ID": ["359505"], "MovieMeter film ID": ["864174"], "Academy Awards Database film ID": ["4806"], "Disney A to Z ID": ["guardians-galaxy-vol-2-film"], "narrative location": ["Missouri"], "Quora topic ID": ["Guardians-of-the-Galaxy-Vol-2-2017-movie"], "image": ["Groot figure (Guardians of the Galaxy Vol. 2).jpg"], "TV Tropes identifier": ["Film/GuardiansOfTheGalaxyVol2"], "Comic Vine ID": ["4025-2229"], "voice actor": ["Vin Diesel", "Bradley Cooper", "Seth Green", "Miley Cyrus"], "Daum movie ID": ["89871"], "Eiga.com movie ID": ["84133"], "AMPAS collections film ID": ["1280600"], "Medier\u00e5det rating": ["For ages 11 and up"], "FPB rating": ["10-12 PG"], "Disney+ movie ID": ["ZdRX4mMbp1gM"], "Letterboxd film ID": ["guardians-of-the-galaxy-vol-2"]}}