{"Q10967097": {"instance of": ["film"], "publication date": [{"time": "+1950-00-00T00:00:00Z", "timezone": 0, "before": 0, "after": 0, "precision": 9, "calendarmodel": "http://www.wikidata.org/entity/Q1985727"}], "country of origin": ["India"], "original language of film or TV show": ["Hindi"]}, "Q10967181": {"instance of": ["film"], "publication date": [{"time": "+1945-00-00T00:00:00Z", "timezone": 0, "before": 0, "after": 0, "precision": 9, "calendarmodel": "http://www.wikidata.org/entity/Q1985727"}], "country of origin": ["British Raj"], "original language of film or TV show": ["Hindi"]}, "Q10967355": {"instance of": ["film"], "publication date": [{"time": "+1951-00-00T00:00:00Z", "timezone": 0, "before": 0, "after": 0, "precision": 9, "calendarmodel": "http://www.wikidata.org/entity/Q1985727"}], "country of origin": ["India"], "original language of film or TV show": ["Hindi"], "cast member": ["Prem Nath"], "IMDb ID": ["tt0130489"]}, "Q10967797": {"instance of": ["film"], "publication date": [{"time": "+1952-00-00T00:00:00Z", "timezone": 0, "before": 0, "after": 0, "precision": 9, "calendarmodel": "http://www.wikidata.org/entity/Q1985727"}], "country of origin": ["India"], "original language of film or TV show": ["Hindi"], "cast member": ["Geeta Bali"], "IMDb ID": ["tt0369269"], "\u010cSFD film ID": ["63613"], "Kinopoisk film ID": ["272338"], "elFilm film ID": ["364176"]}}