{"Q10952512": {"instance of": ["film"], "publication date": [{"time": "+1962-00-00T00:00:00Z", "timezone": 0, "before": 0, "after": 0, "precision": 9, "calendarmodel": "http://www.wikidata.org/entity/Q1985727"}], "country of origin": ["India"], "original language of film or TV show": ["Hindi"], "cast member": ["Manoj Kumar"], "IMDb ID": ["tt0355716"], "Indiancine.ma film ID": ["KJK"]}, "Q10952657": {"IMDb ID": ["tt0305689"], "instance of": ["film"], "cast member": ["Nanda", "Shashi Kapoor", "Agha"], "publication date": [{"time": "+1965-01-01T00:00:00Z", "timezone": 0, "before": 0, "after": 0, "precision": 9, "calendarmodel": "http://www.wikidata.org/entity/Q1985727"}], "original language of film or TV show": ["Hindi"], "country of origin": ["India"], "Kinopoisk film ID": ["95407"], "Rotten Tomatoes ID": ["m/jab-jab-phool-khile"], "\u010cSFD film ID": ["204017"], "elFilm film ID": ["301338"], "PORT film ID": ["134275"], "AllMovie movie ID": ["v408793"], "Douban film ID": ["4217704"], "narrative location": ["Jammu and Kashmir"], "composer": ["Kalyanji\u2013Anandji"], "Indiancine.ma film ID": ["LOQ"], "Letterboxd film ID": ["jab-jab-phool-khile"]}, "Q10952682": {"instance of": ["film"], "publication date": [{"time": "+1964-00-00T00:00:00Z", "timezone": 0, "before": 0, "after": 0, "precision": 9, "calendarmodel": "http://www.wikidata.org/entity/Q1985727"}], "country of origin": ["India"], "original language of film or TV show": ["Hindi"], "IMDb ID": ["tt0371598"], "Indiancine.ma film ID": ["LBD"], "Letterboxd film ID": ["cha-cha-cha-1964"]}, "Q10952710": {"instance of": ["film"], "publication date": [{"time": "+1965-00-00T00:00:00Z", "timezone": 0, "before": 0, "after": 0, "precision": 9, "calendarmodel": "http://www.wikidata.org/entity/Q1985727"}], "country of origin": ["India"], "original language of film or TV show": ["Hindi"], "IMDb ID": ["tt0213635"]}}