{"Q5936551": {"IMDb ID": ["tt0320097"], "instance of": ["film"], "director": ["David Dhawan"], "cast member": ["Amitabh Bachchan", "Sanjay Dutt", "Ajay Devgn", "Aishwarya Rai"], "publication date": [{"time": "+2002-01-01T00:00:00Z", "timezone": 0, "before": 0, "after": 0, "precision": 9, "calendarmodel": "http://www.wikidata.org/entity/Q1985727"}], "original language of film or TV show": ["Hindi"], "country of origin": ["India"], "composer": ["Anu Malik"], "genre": ["drama film", "romantic comedy"], "distributed by": ["T-Series"], "Kinopoisk film ID": ["39664"], "OFDb ID": ["69870"], "color": ["color"], "director of photography": ["Manmohan Singh"], "film editor": ["David Dhawan"], "\u010cSFD film ID": ["159102"], "PORT film ID": ["130548"], "FilmAffinity ID": ["843104"], "elFilm film ID": ["315572"], "Indiancine.ma film ID": ["ASDI"]}, "Q5936595": {"IMDb ID": ["tt0378069"], "instance of": ["film"], "director": ["Deepak Bahry"], "cast member": ["Mithun Chakraborty", "Amjad Khan", "Danny Denzongpa", "Raja Birbal"], "publication date": [{"time": "+1981-01-01T00:00:00Z", "timezone": 0, "before": 0, "after": 0, "precision": 9, "calendarmodel": "http://www.wikidata.org/entity/Q1985727"}], "original language of film or TV show": ["Hindi"], "country of origin": ["India"], "Kinopoisk film ID": ["264176"], "composer": ["Raam Laxman"], "color": ["color"], "\u010cSFD film ID": ["266718"], "elFilm film ID": ["372824"], "Letterboxd film ID": ["hum-se-badkar-kaun"]}, "Q5936598": {"IMDb ID": ["tt0268373"], "instance of": ["film"], "director": ["Deepak Bahry"], "original language of film or TV show": ["Hindi"], "cast member": ["Mithun Chakraborty", "Zeenat Aman", "Amjad Khan", "Danny Denzongpa", "Ranjeet", "Bob Christo"], "country of origin": ["India"], "publication date": [{"time": "+1983-00-00T00:00:00Z", "timezone": 0, "before": 0, "after": 0, "precision": 9, "calendarmodel": "http://www.wikidata.org/entity/Q1985727"}], "Kinopoisk film ID": ["224682"], "color": ["color"], "Rotten Tomatoes ID": ["m/hum-se-hai-zamana"], "\u010cSFD film ID": ["266676"], "AllMovie movie ID": ["v564221"], "elFilm film ID": ["264568"], "composer": ["Raam Laxman"], "genre": ["action film"], "Letterboxd film ID": ["hum-se-hai-zamana"]}, "Q5936603": {"IMDb ID": ["tt0359444"], "instance of": ["film"], "director": ["Deepak Bahry"], "cast member": ["Dharmendra", "Shatrughan Sinha", "Mithun Chakraborty", "Kimi Katkar", "Anita Raj"], "producer": ["Deepak Bahry"], "publication date": [{"time": "+1990-01-01T00:00:00Z", "timezone": 0, "before": 0, "after": 0, "precision": 9, "calendarmodel": "http://www.wikidata.org/entity/Q1985727"}], "original language of film or TV show": ["Hindi"], "country of origin": ["India"], "Kinopoisk film ID": ["208327"], "OFDb ID": ["232219"], "color": ["color"], "elFilm film ID": ["354529"], "\u010cSFD film ID": ["265486"], "composer": ["Laxmikant-Pyarelal"]}}